fun_maths/__init__.py
fun_maths/constants/__init__.py
fun_math-0.1.dist-info/METADATA
fun_math-0.1.dist-info/WHEEL
fun_math-0.1.dist-info/top_level.txt
fun_math-0.1.dist-info/RECORD
