Metadata-Version: 2.1
Name: fun-math
Version: 0.1
Summary: some useful maths
Home-page: UNKNOWN
Author: Allen Sun
Author-email: allen.haha@hotmail.com
License: UNKNOWN
Platform: UNKNOWN
Classifier: Development Status :: 2 - Pre-Alpha
Classifier: Programming Language :: Python :: 3
Classifier: License :: OSI Approved :: MIT License
Classifier: Operating System :: OS Independent
Requires-Python: >=3.6
